[{"id":"N0","name":"Sasha","age":36},{"id":"N1","name":"Sergei","age":36},{"id":"N2","name":"Sasha","age":22},{"id":"N3","name":"Kolya","age":30},{"id":"N4","name":"Sasha","age":35},{"id":"N5","name":"Yana","age":40},{"id":"N6","name":"Yana","age":31},{"id":"N7","name":"Yana","age":22},{"id":"N8","name":"Dima","age":24},{"id":"N9","name":"Sasha","age":24},{"id":"N10","name":"Sergei","age":29},{"id":"N11","name":"Kolya","age":26},{"id":"N12","name":"Sergei","age":26},{"id":"N13","name":"Sergei","age":41},{"id":"N14","name":"Sergei","age":22},{"id":"N15","name":"Yana","age":31},{"id":"N16","name":"Kolya","age":38},{"id":"N17","name":"Sergei","age":43},{"id":"N18","name":"Sasha","age":31},{"id":"N19","name":"Kolya","age":32},{"id":"N20","name":"Sasha","age":42},{"id":"N21","name":"Sasha","age":43},{"id":"N22","name":"Dima","age":43},{"id":"N23","name":"Dima","age":35},{"id":"N24","name":"Sergei","age":32},{"id":"N25","name":"Dima","age":45},{"id":"N26","name":"Dima","age":34},{"id":"N27","name":"Kolya","age":29},{"id":"N28","name":"Yana","age":41},{"id":"N29","name":"Kolya","age":24},{"id":"N30","name":"Sasha","age":34},{"id":"N31","name":"Yana","age":31},{"id":"N32","name":"Sergei","age":26},{"id":"N33","name":"Sergei","age":18},{"id":"N34","name":"Sasha","age":28},{"id":"N35","name":"Yana","age":20},{"id":"N36","name":"Yana","age":29},{"id":"N37","name":"Sergei","age":42},{"id":"N38","name":"Kolya","age":25},{"id":"N39","name":"Sergei","age":42},{"id":"N40","name":"Dima","age":25},{"id":"N41","name":"Sergei","age":27},{"id":"N42","name":"Kolya","age":21},{"id":"N43","name":"Sergei","age":41},{"id":"N44","name":"Dima","age":42},{"id":"N45","name":"Sergei","age":37},{"id":"N46","name":"Sasha","age":23},{"id":"N47","name":"Kolya","age":38},{"id":"N48","name":"Yana","age":40},{"id":"N49","name":"Sasha","age":45}]